{"form": [{"text": "Brett Milano", "box": [322, 70, 452, 93], "words": [{"box": [322, 70, 376, 93], "text": "Brett"}, {"box": [383, 70, 452, 93], "text": "Milano"}], "label": "Name", "linking": [], "id": 0}, {"text": "116 Newland Rd., Arlington MA 02474", "box": [269, 96, 503, 110], "words": [{"box": [269, 96, 291, 110], "text": "116"}, {"box": [295, 96, 349, 110], "text": "Newland"}, {"box": [353, 96, 379, 110], "text": "Rd.,"}, {"box": [383, 96, 440, 110], "text": "Arlington"}, {"box": [444, 96, 462, 110], "text": "MA"}, {"box": [466, 96, 503, 110], "text": "02474"}], "label": "Address", "linking": [], "id": 1}, {"text": "617-460-7859", "box": [268, 112, 351, 126], "words": [{"box": [268, 112, 351, 126], "text": "617-460-7859"}], "label": "Phone", "linking": [], "id": 2}, {"text": "muso@mindspring.com", "box": [366, 112, 508, 126], "words": [{"box": [366, 112, 508, 126], "text": "muso@mindspring.com"}], "label": "Email", "linking": [], "id": 3}, {"text": "/", "box": [355, 112, 362, 126], "words": [{"box": [355, 112, 362, 126], "text": "/"}], "label": "Other", "linking": [], "id": 4}, {"text": "____________________________________________________________________", "box": [139, 128, 633, 142], "words": [{"box": [139, 128, 633, 142], "text": "____________________________________________________________________"}], "label": "Other", "linking": [], "id": 5}, {"text": "Profile", "box": [362, 162, 410, 177], "words": [{"box": [362, 162, 410, 177], "text": "Profile"}], "label": "Other", "linking": [], "id": 6}, {"text": "Communications", "box": [114, 197, 216, 211], "words": [{"box": [114, 197, 216, 211], "text": "Communications"}], "label": "Other", "linking": [], "id": 7}, {"text": "professional", "box": [220, 197, 295, 211], "words": [{"box": [220, 197, 295, 211], "text": "professional"}], "label": "Other", "linking": [], "id": 8}, {"text": "with", "box": [299, 197, 326, 211], "words": [{"box": [299, 197, 326, 211], "text": "with"}], "label": "Other", "linking": [], "id": 9}, {"text": "comprehensive", "box": [330, 197, 423, 211], "words": [{"box": [330, 197, 423, 211], "text": "comprehensive"}], "label": "Other", "linking": [], "id": 10}, {"text": "experience", "box": [428, 197, 497, 211], "words": [{"box": [428, 197, 497, 211], "text": "experience"}], "label": "Other", "linking": [], "id": 11}, {"text": "in", "box": [501, 197, 512, 211], "words": [{"box": [501, 197, 512, 211], "text": "in"}], "label": "Other", "linking": [], "id": 12}, {"text": "creative,", "box": [517, 197, 573, 211], "words": [{"box": [517, 197, 573, 211], "text": "creative,"}], "label": "Other", "linking": [], "id": 13}, {"text": "academic,", "box": [577, 197, 641, 211], "words": [{"box": [577, 197, 641, 211], "text": "academic,"}], "label": "Other", "linking": [], "id": 14}, {"text": "and", "box": [114, 213, 136, 227], "words": [{"box": [114, 213, 136, 227], "text": "and"}], "label": "Other", "linking": [], "id": 15}, {"text": "corporate", "box": [140, 213, 201, 227], "words": [{"box": [140, 213, 201, 227], "text": "corporate"}], "label": "Other", "linking": [], "id": 16}, {"text": "environments", "box": [205, 213, 289, 227], "words": [{"box": [205, 213, 289, 227], "text": "environments"}], "label": "Other", "linking": [], "id": 17}, {"text": "and", "box": [293, 213, 316, 227], "words": [{"box": [293, 213, 316, 227], "text": "and"}], "label": "Other", "linking": [], "id": 18}, {"text": "copywriting,", "box": [320, 213, 398, 227], "words": [{"box": [320, 213, 398, 227], "text": "copywriting,"}], "label": "Other", "linking": [], "id": 19}, {"text": "marketing", "box": [402, 213, 465, 227], "words": [{"box": [402, 213, 465, 227], "text": "marketing"}], "label": "Other", "linking": [], "id": 20}, {"text": "and", "box": [469, 213, 492, 227], "words": [{"box": [469, 213, 492, 227], "text": "and"}], "label": "Other", "linking": [], "id": 21}, {"text": "editing", "box": [496, 213, 539, 227], "words": [{"box": [496, 213, 539, 227], "text": "editing"}], "label": "Other", "linking": [], "id": 22}, {"text": "experience", "box": [543, 213, 612, 227], "words": [{"box": [543, 213, 612, 227], "text": "experience"}], "label": "Other", "linking": [], "id": 23}, {"text": "in", "box": [616, 213, 628, 227], "words": [{"box": [616, 213, 628, 227], "text": "in"}], "label": "Other", "linking": [], "id": 24}, {"text": "print", "box": [114, 229, 144, 243], "words": [{"box": [114, 229, 144, 243], "text": "print"}], "label": "Other", "linking": [], "id": 25}, {"text": "journalism", "box": [148, 229, 213, 243], "words": [{"box": [148, 229, 213, 243], "text": "journalism"}], "label": "Other", "linking": [], "id": 26}, {"text": "and", "box": [218, 229, 240, 243], "words": [{"box": [218, 229, 240, 243], "text": "and"}], "label": "Other", "linking": [], "id": 27}, {"text": "digital", "box": [244, 229, 284, 243], "words": [{"box": [244, 229, 284, 243], "text": "digital"}], "label": "Other", "linking": [], "id": 28}, {"text": "media.", "box": [288, 229, 331, 243], "words": [{"box": [288, 229, 331, 243], "text": "media."}], "label": "Other", "linking": [], "id": 29}, {"text": "Areas", "box": [321, 278, 361, 293], "words": [{"box": [321, 278, 361, 293], "text": "Areas"}], "label": "Other", "linking": [], "id": 30}, {"text": "of", "box": [365, 278, 379, 293], "words": [{"box": [365, 278, 379, 293], "text": "of"}], "label": "Other", "linking": [], "id": 31}, {"text": "Expertise", "box": [384, 278, 451, 293], "words": [{"box": [384, 278, 451, 293], "text": "Expertise"}], "label": "Other", "linking": [], "id": 32}, {"text": "\u2022", "box": [136, 311, 143, 325], "words": [{"box": [136, 311, 143, 325], "text": "\u2022"}], "label": "Other", "linking": [], "id": 33}, {"text": "\u2022", "box": [136, 328, 143, 342], "words": [{"box": [136, 328, 143, 342], "text": "\u2022"}], "label": "Other", "linking": [], "id": 34}, {"text": "\u2022", "box": [136, 345, 143, 359], "words": [{"box": [136, 345, 143, 359], "text": "\u2022"}], "label": "Other", "linking": [], "id": 35}, {"text": "\u2022", "box": [136, 362, 143, 376], "words": [{"box": [136, 362, 143, 376], "text": "\u2022"}], "label": "Other", "linking": [], "id": 36}, {"text": "Copywriting", "box": [159, 314, 236, 328], "words": [{"box": [159, 314, 236, 328], "text": "Copywriting"}], "label": "Other", "linking": [], "id": 37}, {"text": "Online", "box": [159, 331, 201, 345], "words": [{"box": [159, 331, 201, 345], "text": "Online"}], "label": "Other", "linking": [], "id": 38}, {"text": "community", "box": [206, 331, 278, 345], "words": [{"box": [206, 331, 278, 345], "text": "community"}], "label": "Other", "linking": [], "id": 39}, {"text": "building", "box": [282, 331, 334, 345], "words": [{"box": [282, 331, 334, 345], "text": "building"}], "label": "Other", "linking": [], "id": 40}, {"text": "Promotional", "box": [159, 348, 238, 362], "words": [{"box": [159, 348, 238, 362], "text": "Promotional"}], "label": "Other", "linking": [], "id": 41}, {"text": "materials", "box": [242, 348, 302, 362], "words": [{"box": [242, 348, 302, 362], "text": "materials"}], "label": "Other", "linking": [], "id": 42}, {"text": "Social", "box": [159, 365, 197, 379], "words": [{"box": [159, 365, 197, 379], "text": "Social"}], "label": "Other", "linking": [], "id": 43}, {"text": "media", "box": [201, 365, 240, 379], "words": [{"box": [201, 365, 240, 379], "text": "media"}], "label": "Other", "linking": [], "id": 44}, {"text": "strategy", "box": [245, 365, 297, 379], "words": [{"box": [245, 365, 297, 379], "text": "strategy"}], "label": "Other", "linking": [], "id": 45}, {"text": "\u2022", "box": [431, 311, 438, 325], "words": [{"box": [431, 311, 438, 325], "text": "\u2022"}], "label": "Other", "linking": [], "id": 46}, {"text": "\u2022", "box": [431, 328, 438, 342], "words": [{"box": [431, 328, 438, 342], "text": "\u2022"}], "label": "Other", "linking": [], "id": 47}, {"text": "\u2022", "box": [431, 345, 438, 359], "words": [{"box": [431, 345, 438, 359], "text": "\u2022"}], "label": "Other", "linking": [], "id": 48}, {"text": "\u2022", "box": [431, 362, 438, 376], "words": [{"box": [431, 362, 438, 376], "text": "\u2022"}], "label": "Other", "linking": [], "id": 49}, {"text": "Arts", "box": [454, 314, 480, 328], "words": [{"box": [454, 314, 480, 328], "text": "Arts"}], "label": "Other", "linking": [], "id": 50}, {"text": "journalism", "box": [485, 314, 553, 328], "words": [{"box": [485, 314, 553, 328], "text": "journalism"}], "label": "Other", "linking": [], "id": 51}, {"text": "Freelance", "box": [454, 331, 519, 345], "words": [{"box": [454, 331, 519, 345], "text": "Freelance"}], "label": "Other", "linking": [], "id": 52}, {"text": "staff", "box": [523, 331, 553, 345], "words": [{"box": [523, 331, 553, 345], "text": "staff"}], "label": "Other", "linking": [], "id": 53}, {"text": "management", "box": [557, 331, 640, 345], "words": [{"box": [557, 331, 640, 345], "text": "management"}], "label": "Other", "linking": [], "id": 54}, {"text": "Copy", "box": [454, 348, 486, 362], "words": [{"box": [454, 348, 486, 362], "text": "Copy"}], "label": "Other", "linking": [], "id": 55}, {"text": "editing", "box": [490, 348, 535, 362], "words": [{"box": [490, 348, 535, 362], "text": "editing"}], "label": "Other", "linking": [], "id": 56}, {"text": "Email", "box": [454, 365, 490, 379], "words": [{"box": [454, 365, 490, 379], "text": "Email"}], "label": "Other", "linking": [], "id": 57}, {"text": "promotions", "box": [494, 365, 567, 379], "words": [{"box": [494, 365, 567, 379], "text": "promotions"}], "label": "Other", "linking": [], "id": 58}, {"text": "Professional", "box": [312, 430, 398, 445], "words": [{"box": [312, 430, 398, 445], "text": "Professional"}], "label": "Other", "linking": [], "id": 59}, {"text": "Experience", "box": [403, 430, 482, 445], "words": [{"box": [403, 430, 482, 445], "text": "Experience"}], "label": "Other", "linking": [], "id": 60}, {"text": "COMPANY", "box": [136, 463, 197, 477], "words": [{"box": [136, 463, 197, 477], "text": "COMPANY"}], "label": "Other", "linking": [], "id": 61}, {"text": "CUE,", "box": [201, 463, 231, 477], "words": [{"box": [201, 463, 231, 477], "text": "CUE,"}], "label": "Other", "linking": [], "id": 62}, {"text": "Croton-on-Hudson,", "box": [235, 463, 352, 477], "words": [{"box": [235, 463, 352, 477], "text": "Croton-on-Hudson,"}], "label": "Other", "linking": [], "id": 63}, {"text": "NY", "box": [356, 463, 373, 477], "words": [{"box": [356, 463, 373, 477], "text": "NY"}], "label": "Other", "linking": [], "id": 64}, {"text": "2015", "box": [627, 463, 656, 477], "words": [{"box": [627, 463, 656, 477], "text": "2015"}], "label": "Other", "linking": [], "id": 65}, {"text": "Writer", "box": [136, 479, 180, 493], "words": [{"box": [136, 479, 180, 493], "text": "Writer"}], "label": "Other", "linking": [], "id": 66}, {"text": "and", "box": [184, 479, 209, 493], "words": [{"box": [184, 479, 209, 493], "text": "and"}], "label": "Other", "linking": [], "id": 67}, {"text": "Content", "box": [213, 479, 265, 493], "words": [{"box": [213, 479, 265, 493], "text": "Content"}], "label": "Other", "linking": [], "id": 68}, {"text": "Manager", "box": [269, 479, 326, 493], "words": [{"box": [269, 479, 326, 493], "text": "Manager"}], "label": "Other", "linking": [], "id": 69}, {"text": "\u2022", "box": [157, 495, 165, 509], "words": [{"box": [157, 495, 165, 509], "text": "\u2022"}], "label": "Other", "linking": [], "id": 70}, {"text": "Managed", "box": [182, 495, 236, 509], "words": [{"box": [182, 495, 236, 509], "text": "Managed"}], "label": "Other", "linking": [], "id": 71}, {"text": "product-related", "box": [240, 495, 339, 509], "words": [{"box": [240, 495, 339, 509], "text": "product-related"}], "label": "Other", "linking": [], "id": 72}, {"text": "content", "box": [343, 495, 391, 509], "words": [{"box": [343, 495, 391, 509], "text": "content"}], "label": "Other", "linking": [], "id": 73}, {"text": "for", "box": [395, 495, 413, 509], "words": [{"box": [395, 495, 413, 509], "text": "for"}], "label": "Other", "linking": [], "id": 74}, {"text": "a", "box": [417, 495, 425, 509], "words": [{"box": [417, 495, 425, 509], "text": "a"}], "label": "Other", "linking": [], "id": 75}, {"text": "major", "box": [429, 495, 466, 509], "words": [{"box": [429, 495, 466, 509], "text": "major"}], "label": "Other", "linking": [], "id": 76}, {"text": "international", "box": [470, 495, 550, 509], "words": [{"box": [470, 495, 550, 509], "text": "international"}], "label": "Other", "linking": [], "id": 77}, {"text": "client.", "box": [555, 495, 595, 509], "words": [{"box": [555, 495, 595, 509], "text": "client."}], "label": "Other", "linking": [], "id": 78}, {"text": "OFFBEAT", "box": [136, 528, 192, 542], "words": [{"box": [136, 528, 192, 542], "text": "OFFBEAT"}], "label": "Other", "linking": [], "id": 79}, {"text": "MAGAZINE,", "box": [196, 528, 265, 542], "words": [{"box": [196, 528, 265, 542], "text": "MAGAZINE,"}], "label": "Other", "linking": [], "id": 80}, {"text": "New", "box": [269, 528, 296, 542], "words": [{"box": [269, 528, 296, 542], "text": "New"}], "label": "Other", "linking": [], "id": 81}, {"text": "Orleans,", "box": [300, 528, 352, 542], "words": [{"box": [300, 528, 352, 542], "text": "Orleans,"}], "label": "Other", "linking": [], "id": 82}, {"text": "LA", "box": [356, 528, 371, 542], "words": [{"box": [356, 528, 371, 542], "text": "LA"}], "label": "Other", "linking": [], "id": 83}, {"text": "Print", "box": [136, 544, 169, 558], "words": [{"box": [136, 544, 169, 558], "text": "Print"}], "label": "Other", "linking": [], "id": 84}, {"text": "and", "box": [173, 544, 198, 558], "words": [{"box": [173, 544, 198, 558], "text": "and"}], "label": "Other", "linking": [], "id": 85}, {"text": "Online", "box": [202, 544, 244, 558], "words": [{"box": [202, 544, 244, 558], "text": "Online"}], "label": "Other", "linking": [], "id": 86}, {"text": "Editor", "box": [249, 544, 290, 558], "words": [{"box": [249, 544, 290, 558], "text": "Editor"}], "label": "Other", "linking": [], "id": 87}, {"text": "2012-2014", "box": [590, 528, 653, 542], "words": [{"box": [590, 528, 653, 542], "text": "2012-2014"}], "label": "Other", "linking": [], "id": 88}, {"text": "\u2022", "box": [159, 558, 165, 572], "words": [{"box": [159, 558, 165, 572], "text": "\u2022"}], "label": "Other", "linking": [], "id": 89}, {"text": "\u2022", "box": [159, 591, 165, 605], "words": [{"box": [159, 591, 165, 605], "text": "\u2022"}], "label": "Other", "linking": [], "id": 90}, {"text": "\u2022", "box": [159, 608, 165, 622], "words": [{"box": [159, 608, 165, 622], "text": "\u2022"}], "label": "Other", "linking": [], "id": 91}, {"text": "\u2022", "box": [159, 625, 165, 639], "words": [{"box": [159, 625, 165, 639], "text": "\u2022"}], "label": "Other", "linking": [], "id": 92}, {"text": "\u2022", "box": [159, 642, 165, 656], "words": [{"box": [159, 642, 165, 656], "text": "\u2022"}], "label": "Other", "linking": [], "id": 93}, {"text": "\u2022", "box": [159, 659, 165, 673], "words": [{"box": [159, 659, 165, 673], "text": "\u2022"}], "label": "Other", "linking": [], "id": 94}, {"text": "\u2022", "box": [159, 676, 165, 690], "words": [{"box": [159, 676, 165, 690], "text": "\u2022"}], "label": "Other", "linking": [], "id": 95}, {"text": "\u2022", "box": [159, 709, 165, 723], "words": [{"box": [159, 709, 165, 723], "text": "\u2022"}], "label": "Other", "linking": [], "id": 96}, {"text": "Wrote,", "box": [182, 561, 224, 575], "words": [{"box": [182, 561, 224, 575], "text": "Wrote,"}], "label": "Other", "linking": [], "id": 97}, {"text": "researched,", "box": [229, 561, 302, 575], "words": [{"box": [229, 561, 302, 575], "text": "researched,"}], "label": "Other", "linking": [], "id": 98}, {"text": "edited", "box": [307, 561, 347, 575], "words": [{"box": [307, 561, 347, 575], "text": "edited"}], "label": "Other", "linking": [], "id": 99}, {"text": "and", "box": [351, 561, 374, 575], "words": [{"box": [351, 561, 374, 575], "text": "and"}], "label": "Other", "linking": [], "id": 100}, {"text": "programmed", "box": [378, 561, 456, 575], "words": [{"box": [378, 561, 456, 575], "text": "programmed"}], "label": "Other", "linking": [], "id": 101}, {"text": "playlist", "box": [461, 561, 506, 575], "words": [{"box": [461, 561, 506, 575], "text": "playlist"}], "label": "Other", "linking": [], "id": 102}, {"text": "content", "box": [510, 561, 558, 575], "words": [{"box": [510, 561, 558, 575], "text": "content"}], "label": "Other", "linking": [], "id": 103}, {"text": "for", "box": [562, 561, 580, 575], "words": [{"box": [562, 561, 580, 575], "text": "for"}], "label": "Other", "linking": [], "id": 104}, {"text": "a", "box": [584, 561, 592, 575], "words": [{"box": [584, 561, 592, 575], "text": "a"}], "label": "Other", "linking": [], "id": 105}, {"text": "major", "box": [596, 561, 633, 575], "words": [{"box": [596, 561, 633, 575], "text": "major"}], "label": "Other", "linking": [], "id": 106}, {"text": "international", "box": [182, 577, 262, 591], "words": [{"box": [182, 577, 262, 591], "text": "international"}], "label": "Other", "linking": [], "id": 107}, {"text": "client\u2019s", "box": [266, 577, 313, 591], "words": [{"box": [266, 577, 313, 591], "text": "client\u2019s"}], "label": "Other", "linking": [], "id": 108}, {"text": "music-streaming", "box": [317, 577, 419, 591], "words": [{"box": [317, 577, 419, 591], "text": "music-streaming"}], "label": "Other", "linking": [], "id": 109}, {"text": "project.", "box": [423, 577, 474, 591], "words": [{"box": [423, 577, 474, 591], "text": "project."}], "label": "Other", "linking": [], "id": 110}, {"text": "Oversaw", "box": [182, 594, 234, 608], "words": [{"box": [182, 594, 234, 608], "text": "Oversaw"}], "label": "Other", "linking": [], "id": 111}, {"text": "all", "box": [238, 594, 254, 608], "words": [{"box": [238, 594, 254, 608], "text": "all"}], "label": "Other", "linking": [], "id": 112}, {"text": "content", "box": [258, 594, 306, 608], "words": [{"box": [258, 594, 306, 608], "text": "content"}], "label": "Other", "linking": [], "id": 113}, {"text": "for", "box": [310, 594, 328, 608], "words": [{"box": [310, 594, 328, 608], "text": "for"}], "label": "Other", "linking": [], "id": 114}, {"text": "leading", "box": [332, 594, 377, 608], "words": [{"box": [332, 594, 377, 608], "text": "leading"}], "label": "Other", "linking": [], "id": 115}, {"text": "New", "box": [382, 594, 409, 608], "words": [{"box": [382, 594, 409, 608], "text": "New"}], "label": "Other", "linking": [], "id": 116}, {"text": "Orleans", "box": [413, 594, 460, 608], "words": [{"box": [413, 594, 460, 608], "text": "Orleans"}], "label": "Other", "linking": [], "id": 117}, {"text": "arts", "box": [464, 594, 488, 608], "words": [{"box": [464, 594, 488, 608], "text": "arts"}], "label": "Other", "linking": [], "id": 118}, {"text": "and", "box": [492, 594, 514, 608], "words": [{"box": [492, 594, 514, 608], "text": "and"}], "label": "Other", "linking": [], "id": 119}, {"text": "culture", "box": [519, 594, 563, 608], "words": [{"box": [519, 594, 563, 608], "text": "culture"}], "label": "Other", "linking": [], "id": 120}, {"text": "monthly.", "box": [568, 594, 623, 608], "words": [{"box": [568, 594, 623, 608], "text": "monthly."}], "label": "Other", "linking": [], "id": 121}, {"text": "Managed", "box": [182, 611, 236, 625], "words": [{"box": [182, 611, 236, 625], "text": "Managed"}], "label": "Other", "linking": [], "id": 122}, {"text": "a", "box": [240, 611, 247, 625], "words": [{"box": [240, 611, 247, 625], "text": "a"}], "label": "Other", "linking": [], "id": 123}, {"text": "team", "box": [252, 611, 283, 625], "words": [{"box": [252, 611, 283, 625], "text": "team"}], "label": "Other", "linking": [], "id": 124}, {"text": "of", "box": [288, 611, 300, 625], "words": [{"box": [288, 611, 300, 625], "text": "of"}], "label": "Other", "linking": [], "id": 125}, {"text": "freelance", "box": [304, 611, 364, 625], "words": [{"box": [304, 611, 364, 625], "text": "freelance"}], "label": "Other", "linking": [], "id": 126}, {"text": "writers,", "box": [368, 611, 417, 625], "words": [{"box": [368, 611, 417, 625], "text": "writers,"}], "label": "Other", "linking": [], "id": 127}, {"text": "photographers,", "box": [421, 611, 515, 625], "words": [{"box": [421, 611, 515, 625], "text": "photographers,"}], "label": "Other", "linking": [], "id": 128}, {"text": "and", "box": [519, 611, 542, 625], "words": [{"box": [519, 611, 542, 625], "text": "and"}], "label": "Other", "linking": [], "id": 129}, {"text": "designers.", "box": [546, 611, 609, 625], "words": [{"box": [546, 611, 609, 625], "text": "designers."}], "label": "Other", "linking": [], "id": 130}, {"text": "Edited,", "box": [182, 628, 227, 642], "words": [{"box": [182, 628, 227, 642], "text": "Edited,"}], "label": "Other", "linking": [], "id": 131}, {"text": "wrote,", "box": [231, 628, 272, 642], "words": [{"box": [231, 628, 272, 642], "text": "wrote,"}], "label": "Other", "linking": [], "id": 132}, {"text": "and", "box": [276, 628, 299, 642], "words": [{"box": [276, 628, 299, 642], "text": "and"}], "label": "Other", "linking": [], "id": 133}, {"text": "produced", "box": [303, 628, 361, 642], "words": [{"box": [303, 628, 361, 642], "text": "produced"}], "label": "Other", "linking": [], "id": 134}, {"text": "weekly", "box": [365, 628, 409, 642], "words": [{"box": [365, 628, 409, 642], "text": "weekly"}], "label": "Other", "linking": [], "id": 135}, {"text": "email", "box": [413, 628, 447, 642], "words": [{"box": [413, 628, 447, 642], "text": "email"}], "label": "Other", "linking": [], "id": 136}, {"text": "blast,", "box": [452, 628, 487, 642], "words": [{"box": [452, 628, 487, 642], "text": "blast,"}], "label": "Other", "linking": [], "id": 137}, {"text": "The", "box": [491, 628, 514, 642], "words": [{"box": [491, 628, 514, 642], "text": "The"}], "label": "Other", "linking": [], "id": 138}, {"text": "Weekly", "box": [519, 628, 563, 642], "words": [{"box": [519, 628, 563, 642], "text": "Weekly"}], "label": "Other", "linking": [], "id": 139}, {"text": "Beat.", "box": [568, 628, 601, 642], "words": [{"box": [568, 628, 601, 642], "text": "Beat."}], "label": "Other", "linking": [], "id": 140}, {"text": "Represented", "box": [182, 645, 260, 659], "words": [{"box": [182, 645, 260, 659], "text": "Represented"}], "label": "Other", "linking": [], "id": 141}, {"text": "OffBeat", "box": [264, 645, 313, 659], "words": [{"box": [264, 645, 313, 659], "text": "OffBeat"}], "label": "Other", "linking": [], "id": 142}, {"text": "at", "box": [317, 645, 330, 659], "words": [{"box": [317, 645, 330, 659], "text": "at"}], "label": "Other", "linking": [], "id": 143}, {"text": "awards", "box": [334, 645, 378, 659], "words": [{"box": [334, 645, 378, 659], "text": "awards"}], "label": "Other", "linking": [], "id": 144}, {"text": "ceremonies", "box": [382, 645, 453, 659], "words": [{"box": [382, 645, 453, 659], "text": "ceremonies"}], "label": "Other", "linking": [], "id": 145}, {"text": "and", "box": [457, 645, 480, 659], "words": [{"box": [457, 645, 480, 659], "text": "and"}], "label": "Other", "linking": [], "id": 146}, {"text": "other", "box": [484, 645, 517, 659], "words": [{"box": [484, 645, 517, 659], "text": "other"}], "label": "Other", "linking": [], "id": 147}, {"text": "public", "box": [522, 645, 560, 659], "words": [{"box": [522, 645, 560, 659], "text": "public"}], "label": "Other", "linking": [], "id": 148}, {"text": "appearances.", "box": [564, 645, 647, 659], "words": [{"box": [564, 645, 647, 659], "text": "appearances."}], "label": "Other", "linking": [], "id": 149}, {"text": "Provided", "box": [182, 662, 236, 676], "words": [{"box": [182, 662, 236, 676], "text": "Provided"}], "label": "Other", "linking": [], "id": 150}, {"text": "daily", "box": [240, 662, 270, 676], "words": [{"box": [240, 662, 270, 676], "text": "daily"}], "label": "Other", "linking": [], "id": 151}, {"text": "news", "box": [274, 662, 305, 676], "words": [{"box": [274, 662, 305, 676], "text": "news"}], "label": "Other", "linking": [], "id": 152}, {"text": "and", "box": [310, 662, 332, 676], "words": [{"box": [310, 662, 332, 676], "text": "and"}], "label": "Other", "linking": [], "id": 153}, {"text": "promotional", "box": [336, 662, 412, 676], "words": [{"box": [336, 662, 412, 676], "text": "promotional"}], "label": "Other", "linking": [], "id": 154}, {"text": "updates", "box": [416, 662, 465, 676], "words": [{"box": [416, 662, 465, 676], "text": "updates"}], "label": "Other", "linking": [], "id": 155}, {"text": "on", "box": [469, 662, 484, 676], "words": [{"box": [469, 662, 484, 676], "text": "on"}], "label": "Other", "linking": [], "id": 156}, {"text": "social", "box": [488, 662, 523, 676], "words": [{"box": [488, 662, 523, 676], "text": "social"}], "label": "Other", "linking": [], "id": 157}, {"text": "media.", "box": [528, 662, 571, 676], "words": [{"box": [528, 662, 571, 676], "text": "media."}], "label": "Other", "linking": [], "id": 158}, {"text": "Received", "box": [182, 679, 238, 693], "words": [{"box": [182, 679, 238, 693], "text": "Received"}], "label": "Other", "linking": [], "id": 159}, {"text": "two", "box": [242, 679, 265, 693], "words": [{"box": [242, 679, 265, 693], "text": "two"}], "label": "Other", "linking": [], "id": 160}, {"text": "New", "box": [270, 679, 296, 693], "words": [{"box": [270, 679, 296, 693], "text": "New"}], "label": "Other", "linking": [], "id": 161}, {"text": "Orleans", "box": [301, 679, 348, 693], "words": [{"box": [301, 679, 348, 693], "text": "Orleans"}], "label": "Other", "linking": [], "id": 162}, {"text": "Press", "box": [352, 679, 384, 693], "words": [{"box": [352, 679, 384, 693], "text": "Press"}], "label": "Other", "linking": [], "id": 163}, {"text": "Club", "box": [388, 679, 416, 693], "words": [{"box": [388, 679, 416, 693], "text": "Club"}], "label": "Other", "linking": [], "id": 164}, {"text": "award", "box": [420, 679, 458, 693], "words": [{"box": [420, 679, 458, 693], "text": "award"}], "label": "Other", "linking": [], "id": 165}, {"text": "nominations", "box": [462, 679, 537, 693], "words": [{"box": [462, 679, 537, 693], "text": "nominations"}], "label": "Other", "linking": [], "id": 166}, {"text": "for", "box": [542, 679, 560, 693], "words": [{"box": [542, 679, 560, 693], "text": "for"}], "label": "Other", "linking": [], "id": 167}, {"text": "pieces", "box": [564, 679, 603, 693], "words": [{"box": [564, 679, 603, 693], "text": "pieces"}], "label": "Other", "linking": [], "id": 168}, {"text": "I", "box": [607, 679, 611, 693], "words": [{"box": [607, 679, 611, 693], "text": "I"}], "label": "Other", "linking": [], "id": 169}, {"text": "authored.", "box": [182, 695, 243, 709], "words": [{"box": [182, 695, 243, 709], "text": "authored."}], "label": "Other", "linking": [], "id": 170}, {"text": "Collaborated", "box": [182, 712, 261, 726], "words": [{"box": [182, 712, 261, 726], "text": "Collaborated"}], "label": "Other", "linking": [], "id": 171}, {"text": "with", "box": [266, 712, 293, 726], "words": [{"box": [266, 712, 293, 726], "text": "with"}], "label": "Other", "linking": [], "id": 172}, {"text": "in-house", "box": [297, 712, 349, 726], "words": [{"box": [297, 712, 349, 726], "text": "in-house"}], "label": "Other", "linking": [], "id": 173}, {"text": "and", "box": [354, 712, 376, 726], "words": [{"box": [354, 712, 376, 726], "text": "and"}], "label": "Other", "linking": [], "id": 174}, {"text": "agency", "box": [380, 712, 424, 726], "words": [{"box": [380, 712, 424, 726], "text": "agency"}], "label": "Other", "linking": [], "id": 175}, {"text": "graphic", "box": [428, 712, 474, 726], "words": [{"box": [428, 712, 474, 726], "text": "graphic"}], "label": "Other", "linking": [], "id": 176}, {"text": "designers", "box": [478, 712, 536, 726], "words": [{"box": [478, 712, 536, 726], "text": "designers"}], "label": "Other", "linking": [], "id": 177}, {"text": "on", "box": [540, 712, 555, 726], "words": [{"box": [540, 712, 555, 726], "text": "on"}], "label": "Other", "linking": [], "id": 178}, {"text": "cover", "box": [559, 712, 594, 726], "words": [{"box": [559, 712, 594, 726], "text": "cover"}], "label": "Other", "linking": [], "id": 179}, {"text": "strategies", "box": [182, 729, 243, 742], "words": [{"box": [182, 729, 243, 742], "text": "strategies"}], "label": "Other", "linking": [], "id": 180}, {"text": "and", "box": [247, 729, 269, 742], "words": [{"box": [247, 729, 269, 742], "text": "and"}], "label": "Other", "linking": [], "id": 181}, {"text": "advertising", "box": [273, 729, 342, 742], "words": [{"box": [273, 729, 342, 742], "text": "advertising"}], "label": "Other", "linking": [], "id": 182}, {"text": "campaigns.", "box": [346, 729, 416, 742], "words": [{"box": [346, 729, 416, 742], "text": "campaigns."}], "label": "Other", "linking": [], "id": 183}, {"text": "FREELANCE,", "box": [136, 763, 212, 777], "words": [{"box": [136, 763, 212, 777], "text": "FREELANCE,"}], "label": "Other", "linking": [], "id": 184}, {"text": "Boston,", "box": [216, 763, 262, 777], "words": [{"box": [216, 763, 262, 777], "text": "Boston,"}], "label": "Other", "linking": [], "id": 185}, {"text": "MA", "box": [267, 763, 285, 777], "words": [{"box": [267, 763, 285, 777], "text": "MA"}], "label": "Other", "linking": [], "id": 186}, {"text": "Writer,", "box": [136, 782, 185, 796], "words": [{"box": [136, 782, 185, 796], "text": "Writer,"}], "label": "Other", "linking": [], "id": 187}, {"text": "Editor,", "box": [189, 782, 236, 796], "words": [{"box": [189, 782, 236, 796], "text": "Editor,"}], "label": "Other", "linking": [], "id": 188}, {"text": "and", "box": [240, 782, 264, 796], "words": [{"box": [240, 782, 264, 796], "text": "and"}], "label": "Other", "linking": [], "id": 189}, {"text": "Author", "box": [269, 782, 313, 796], "words": [{"box": [269, 782, 313, 796], "text": "Author"}], "label": "Other", "linking": [], "id": 190}, {"text": "1995-2012", "box": [590, 763, 654, 777], "words": [{"box": [590, 763, 654, 777], "text": "1995-2012"}], "label": "Other", "linking": [], "id": 191}, {"text": "\u2022", "box": [159, 798, 165, 812], "words": [{"box": [159, 798, 165, 812], "text": "\u2022"}], "label": "Other", "linking": [], "id": 192}, {"text": "\u2022", "box": [159, 831, 165, 845], "words": [{"box": [159, 831, 165, 845], "text": "\u2022"}], "label": "Other", "linking": [], "id": 193}, {"text": "\u2022", "box": [159, 865, 165, 878], "words": [{"box": [159, 865, 165, 878], "text": "\u2022"}], "label": "Other", "linking": [], "id": 194}, {"text": "Published", "box": [182, 801, 241, 815], "words": [{"box": [182, 801, 241, 815], "text": "Published"}], "label": "Other", "linking": [], "id": 195}, {"text": "first", "box": [245, 801, 271, 815], "words": [{"box": [245, 801, 271, 815], "text": "first"}], "label": "Other", "linking": [], "id": 196}, {"text": "book,", "box": [275, 801, 310, 815], "words": [{"box": [275, 801, 310, 815], "text": "book,"}], "label": "Other", "linking": [], "id": 197}, {"text": "Vinyl", "box": [314, 801, 345, 815], "words": [{"box": [314, 801, 345, 815], "text": "Vinyl"}], "label": "Other", "linking": [], "id": 198}, {"text": "Junkies:", "box": [350, 801, 401, 815], "words": [{"box": [350, 801, 401, 815], "text": "Junkies:"}], "label": "Other", "linking": [], "id": 199}, {"text": "Adventures", "box": [405, 801, 476, 815], "words": [{"box": [405, 801, 476, 815], "text": "Adventures"}], "label": "Other", "linking": [], "id": 200}, {"text": "in", "box": [480, 801, 492, 815], "words": [{"box": [480, 801, 492, 815], "text": "in"}], "label": "Other", "linking": [], "id": 201}, {"text": "Record", "box": [496, 801, 539, 815], "words": [{"box": [496, 801, 539, 815], "text": "Record"}], "label": "Other", "linking": [], "id": 202}, {"text": "Collecting", "box": [543, 801, 606, 815], "words": [{"box": [543, 801, 606, 815], "text": "Collecting"}], "label": "Other", "linking": [], "id": 203}, {"text": "through", "box": [610, 801, 658, 815], "words": [{"box": [610, 801, 658, 815], "text": "through"}], "label": "Other", "linking": [], "id": 204}, {"text": "St.", "box": [182, 817, 199, 831], "words": [{"box": [182, 817, 199, 831], "text": "St."}], "label": "Other", "linking": [], "id": 205}, {"text": "Martin\u2019s", "box": [203, 817, 253, 831], "words": [{"box": [203, 817, 253, 831], "text": "Martin\u2019s"}], "label": "Other", "linking": [], "id": 206}, {"text": "Press,", "box": [258, 817, 295, 831], "words": [{"box": [258, 817, 295, 831], "text": "Press,"}], "label": "Other", "linking": [], "id": 207}, {"text": "September", "box": [299, 817, 366, 831], "words": [{"box": [299, 817, 366, 831], "text": "September"}], "label": "Other", "linking": [], "id": 208}, {"text": "2001.", "box": [370, 817, 404, 831], "words": [{"box": [370, 817, 404, 831], "text": "2001."}], "label": "Other", "linking": [], "id": 209}, {"text": "Published", "box": [182, 834, 241, 848], "words": [{"box": [182, 834, 241, 848], "text": "Published"}], "label": "Other", "linking": [], "id": 210}, {"text": "second", "box": [245, 834, 288, 848], "words": [{"box": [245, 834, 288, 848], "text": "second"}], "label": "Other", "linking": [], "id": 211}, {"text": "book,", "box": [292, 834, 327, 848], "words": [{"box": [292, 834, 327, 848], "text": "book,"}], "label": "Other", "linking": [], "id": 212}, {"text": "The", "box": [331, 834, 355, 848], "words": [{"box": [331, 834, 355, 848], "text": "The"}], "label": "Other", "linking": [], "id": 213}, {"text": "Sound", "box": [359, 834, 396, 848], "words": [{"box": [359, 834, 396, 848], "text": "Sound"}], "label": "Other", "linking": [], "id": 214}, {"text": "of", "box": [400, 834, 413, 848], "words": [{"box": [400, 834, 413, 848], "text": "of"}], "label": "Other", "linking": [], "id": 215}, {"text": "Our", "box": [417, 834, 440, 848], "words": [{"box": [417, 834, 440, 848], "text": "Our"}], "label": "Other", "linking": [], "id": 216}, {"text": "Town:", "box": [444, 834, 483, 848], "words": [{"box": [444, 834, 483, 848], "text": "Town:"}], "label": "Other", "linking": [], "id": 217}, {"text": "A", "box": [487, 834, 496, 848], "words": [{"box": [487, 834, 496, 848], "text": "A"}], "label": "Other", "linking": [], "id": 218}, {"text": "History", "box": [500, 834, 545, 848], "words": [{"box": [500, 834, 545, 848], "text": "History"}], "label": "Other", "linking": [], "id": 219}, {"text": "of", "box": [549, 834, 562, 848], "words": [{"box": [549, 834, 562, 848], "text": "of"}], "label": "Other", "linking": [], "id": 220}, {"text": "Boston", "box": [566, 834, 608, 848], "words": [{"box": [566, 834, 608, 848], "text": "Boston"}], "label": "Other", "linking": [], "id": 221}, {"text": "Rock", "box": [612, 834, 641, 848], "words": [{"box": [612, 834, 641, 848], "text": "Rock"}], "label": "Other", "linking": [], "id": 222}, {"text": "&", "box": [645, 834, 655, 848], "words": [{"box": [645, 834, 655, 848], "text": "&"}], "label": "Other", "linking": [], "id": 223}, {"text": "Roll,", "box": [182, 850, 211, 864], "words": [{"box": [182, 850, 211, 864], "text": "Roll,"}], "label": "Other", "linking": [], "id": 224}, {"text": "through", "box": [215, 850, 263, 864], "words": [{"box": [215, 850, 263, 864], "text": "through"}], "label": "Other", "linking": [], "id": 225}, {"text": "Commonwealth", "box": [268, 850, 364, 864], "words": [{"box": [268, 850, 364, 864], "text": "Commonwealth"}], "label": "Other", "linking": [], "id": 226}, {"text": "Editions,", "box": [368, 850, 422, 864], "words": [{"box": [368, 850, 422, 864], "text": "Editions,"}], "label": "Other", "linking": [], "id": 227}, {"text": "May", "box": [426, 850, 450, 864], "words": [{"box": [426, 850, 450, 864], "text": "May"}], "label": "Other", "linking": [], "id": 228}, {"text": "2007.", "box": [454, 850, 488, 864], "words": [{"box": [454, 850, 488, 864], "text": "2007."}], "label": "Other", "linking": [], "id": 229}, {"text": "Authored", "box": [182, 867, 239, 881], "words": [{"box": [182, 867, 239, 881], "text": "Authored"}], "label": "Other", "linking": [], "id": 230}, {"text": "short", "box": [243, 867, 274, 881], "words": [{"box": [243, 867, 274, 881], "text": "short"}], "label": "Other", "linking": [], "id": 231}, {"text": "stories", "box": [279, 867, 320, 881], "words": [{"box": [279, 867, 320, 881], "text": "stories"}], "label": "Other", "linking": [], "id": 232}, {"text": "in", "box": [324, 867, 335, 881], "words": [{"box": [324, 867, 335, 881], "text": "in"}], "label": "Other", "linking": [], "id": 233}, {"text": "fiction", "box": [339, 867, 380, 881], "words": [{"box": [339, 867, 380, 881], "text": "fiction"}], "label": "Other", "linking": [], "id": 234}, {"text": "anthologies", "box": [384, 867, 455, 881], "words": [{"box": [384, 867, 455, 881], "text": "anthologies"}], "label": "Other", "linking": [], "id": 235}, {"text": "Tales", "box": [459, 867, 492, 881], "words": [{"box": [459, 867, 492, 881], "text": "Tales"}], "label": "Other", "linking": [], "id": 236}, {"text": "From", "box": [496, 867, 528, 881], "words": [{"box": [496, 867, 528, 881], "text": "From"}], "label": "Other", "linking": [], "id": 237}, {"text": "the", "box": [532, 867, 553, 881], "words": [{"box": [532, 867, 553, 881], "text": "the"}], "label": "Other", "linking": [], "id": 238}, {"text": "House", "box": [558, 867, 595, 881], "words": [{"box": [558, 867, 595, 881], "text": "House"}], "label": "Other", "linking": [], "id": 239}, {"text": "Band,", "box": [599, 867, 635, 881], "words": [{"box": [599, 867, 635, 881], "text": "Band,"}], "label": "Other", "linking": [], "id": 240}, {"text": "Volume", "box": [182, 884, 228, 898], "words": [{"box": [182, 884, 228, 898], "text": "Volume"}], "label": "Other", "linking": [], "id": 241}, {"text": "1", "box": [233, 884, 240, 898], "words": [{"box": [233, 884, 240, 898], "text": "1"}], "label": "Other", "linking": [], "id": 242}, {"text": "(Plus", "box": [244, 884, 274, 898], "words": [{"box": [244, 884, 274, 898], "text": "(Plus"}], "label": "Other", "linking": [], "id": 243}, {"text": "One", "box": [278, 884, 303, 898], "words": [{"box": [278, 884, 303, 898], "text": "One"}], "label": "Other", "linking": [], "id": 244}, {"text": "Press,", "box": [307, 884, 344, 898], "words": [{"box": [307, 884, 344, 898], "text": "Press,"}], "label": "Other", "linking": [], "id": 245}, {"text": "2011)", "box": [348, 884, 383, 898], "words": [{"box": [348, 884, 383, 898], "text": "2011)"}], "label": "Other", "linking": [], "id": 246}, {"text": "and", "box": [387, 884, 409, 898], "words": [{"box": [387, 884, 409, 898], "text": "and"}], "label": "Other", "linking": [], "id": 247}, {"text": "Volume", "box": [414, 884, 460, 898], "words": [{"box": [414, 884, 460, 898], "text": "Volume"}], "label": "Other", "linking": [], "id": 248}, {"text": "2", "box": [465, 884, 472, 898], "words": [{"box": [465, 884, 472, 898], "text": "2"}], "label": "Other", "linking": [], "id": 249}, {"text": "(Plus", "box": [476, 884, 506, 898], "words": [{"box": [476, 884, 506, 898], "text": "(Plus"}], "label": "Other", "linking": [], "id": 250}, {"text": "One", "box": [510, 884, 535, 898], "words": [{"box": [510, 884, 535, 898], "text": "One"}], "label": "Other", "linking": [], "id": 251}, {"text": "Press,", "box": [539, 884, 576, 898], "words": [{"box": [539, 884, 576, 898], "text": "Press,"}], "label": "Other", "linking": [], "id": 252}, {"text": "2012).", "box": [581, 884, 620, 898], "words": [{"box": [581, 884, 620, 898], "text": "2012)."}], "label": "Other", "linking": [], "id": 253}]}